scraper_api0/__init__.py
scraper_api0-0.1.0.dist-info/METADATA
scraper_api0-0.1.0.dist-info/WHEEL
scraper_api0-0.1.0.dist-info/RECORD
